{"q+DBL6Ip/DUrNNhuYzaAOQ==":"mbr.jpg","gsjYRdHRUVZKKoL5D2DVIg==":"mbr.jpeg","Jvd/Hv+E6dzGxsxf1OSMGw==":"mbr-1.jpg","Rkh6VN1geuklqasa+Hps8w==":"mbr-2.jpg","OgtCKla7ZhzAplY/dXMFRQ==":"mbr-3.jpg","7cAX25vTViPzsEpxKtfgnw==":"mbr-4.jpg","Bzg68IuBcRh9sFO8XLZmEQ==":"mbr-5.jpg","3L8x5ialuZVROWzapuz4nA==":"mbr-6.jpg","5Yxz1Ro3xgEvJK27QZYsvA==":"mbr-1.jpeg","orRrDp0O7uYYPUWXMASTrg==":"mbr-2.jpeg","hNnJ/ah4jJ+gnKLIjKCM+Q==":"mbr-3.jpeg","8lvp9ISHPOav0iH8GHzE5A==":"mbr-596x397.jpg","7/WNsP1A8OfxYlu8+9v4Xg==":"me-812x1280.jpeg","tTFjtcHK/Ef7JamUl8wY1w==":"1-640x1024.jpeg","OURZBmTdZFst5lF4BUCtYw==":"untitled%2520design-640x1024.png","J1sXiJrNqmwrugl615diBw==":"untitled%2520design-640x1024.png","6flBFsHxGEb9aIH3xaLekA==":"smarttasker-596x499.jpg","PYn7g9Sj/Rbss7+uD+kH/A==":"iot-534x362.jpg","yvgcPEWrmKdigKZIKY+NyA==":"smarttasker-596x499.jpeg","wNh1m3gtK2EOEamkzECJHg==":"smarttasker-1-596x499.jpeg","pN6XKfobsqxpHfqyLf2ZUw==":"swachtrack-596x1152.jpeg","BN7XQKVU3a7L2tBp7UZGSQ==":"swachtrack-1-596x1152.jpeg","KRKqINjHtv1eujp7IoYE8Q==":"iot-534x362.jpeg","Ya8pG2EaHeoEwPZlA7TltQ==":"iot-596x447.jpg","O+o5YOw8N4ZzXLKTPBGDiA==":"me-1-812x1280.jpeg","9jz3R1VM95zoHbS10JXZfA==":"1-1-640x1024.jpeg","vLNY2mAwKnFO7+tvBbz0iw==":"1-2-640x1024.jpeg","/5Fgt/KHTquhp/omOQxIsQ==":"c-883x497.png","sOX0LsiJDla8LZPKJR2Jzw==":"python-225x225.png","r4wSebO/i09vEaBsgjqmlA==":"python-840x430.jpg","Ew007OGOAXRqebdNKHiPZw==":"c-1-883x497.png","mxcTlWOhSymmyNrPdVCidw==":"python-840x430.jpeg","1V5UzTWtpdiQZhV+0df+FQ==":"python-1-840x430.jpeg","ttEPIblWw7Vhq0RYfX0xbQ==":"htmlcss-298x169.jpg","LFzj0RHmyVtNbRUSeDrawg==":"htmlcss-298x169.jpeg","2mo3aaePRRZJ8iEXsQhHVg==":"htmlcss-1-298x169.jpeg","gisnixYbTz3qC4VXzCZUKQ==":"edu-523x741.jpg","v5XFC45qOi7nQVtmmg5VsA==":"edu-523x741.jpeg"}